jax2torch/__init__.py
jax2torch/jax2torch.py
jax2torch-0.0.7.dist-info/LICENSE
jax2torch-0.0.7.dist-info/METADATA
jax2torch-0.0.7.dist-info/WHEEL
jax2torch-0.0.7.dist-info/top_level.txt
jax2torch-0.0.7.dist-info/RECORD
