Metadata-Version: 2.1
Name: jax2torch
Version: 0.0.7
Summary: Jax 2 Torch
Home-page: https://github.com/lucidrains/jax2torch
Author: Phil Wang
Author-email: lucidrains@gmail.com
License: MIT
Keywords: jax,pytorch
Platform: UNKNOWN
Classifier: Development Status :: 4 - Beta
Classifier: Intended Audience :: Developers
Classifier: Topic :: Scientific/Engineering :: Artificial Intelligence
Classifier: License :: OSI Approved :: MIT License
Classifier: Programming Language :: Python :: 3.6
License-File: LICENSE
Requires-Dist: torch (>=1.6)
Requires-Dist: jax (>=0.2.20)
